<?xml version='1.0'?>
<utenti>
    <utente>
        <codiceutente>3</codiceutente>
        <nome>nome3</nome>
        <cognome>cognome3</cognome>
        <datanascita>1990-01-01</datanascita>
        <sesso>1</sesso>
        <password>5f4dcc3b5aa765d61d8327deb882cf99</password>
        <gruppo>3</gruppo>
    </utente>
    <utente>
        <codiceutente>2</codiceutente>
        <nome>nome2</nome>
        <cognome>cognome2</cognome>
        <datanascita>1990-01-01</datanascita>
        <sesso>0</sesso>
        <password>5f4dcc3b5aa765d61d8327deb882cf99</password>
        <gruppo>2</gruppo>
    </utente>
    <utente>
        <codiceutente>1</codiceutente>
        <nome>nome1</nome>
        <cognome>cognome1</cognome>
        <datanascita>1990-01-01</datanascita>
        <sesso>1</sesso>
        <password>5f4dcc3b5aa765d61d8327deb882cf99</password>
        <gruppo>1</gruppo>
    </utente>
    <utente>
        <codiceutente>0</codiceutente>
        <nome>ro</nome>
        <cognome>ot</cognome>
        <password>63a9f0ea7bb98050796b649e85481845</password>
        <gruppo>0</gruppo>
    </utente>
</utenti>
